Workbook
Name aporte: Planilha1!$D$18
Name patrimonio: Planilha1!$D$21
Name qtd_anos: Planilha1!$D$19
Name rendimento: Planilha1!$D$13
Name rendimento_carteira: Planilha1!$D$13
Name salario: Planilha1!$D$12
Name sugestao_investimento: Planilha1!$D$14
Name tx_mensal: Planilha1!$D$20

Sheet Planilha1
B11: CONFIGURAÇÕES
B12: Salário | D12: 1800
B13: Rendimento Carteira | D13: 0.01079
B14: Sugestão de Investimento | D14: =D12*10% -> 180
B17: INVESTIMENTO MENSAL
B18: Quanto investir por mês ? | D18: =sugestao_investimento -> 180
B19: Por quantos anos ? | D19: 10
B20: Taxa de rendimento mensal ? | D20: 0.01079
B21: Patrimônio acumulado? | D21: =FV(tx_mensal,qtd_anos*12,aporte*-1) -> 43791.158
B22: Dividendos mensais? | D22: =patrimonio*rendimento_carteira -> 472.5066
B25: Cenários | D25: Dividendo
A26: 2 | B26: Quantos em 2 anos? | C26: =FV($D$20,$A26*12,$D$18*-1) -> 4900.9729 | D26: =C26*rendimento_carteira -> 52.881498
A27: 5 | B27: Quantos em 5 anos? | C27: =FV($D$20,$A27*12,$D$18*-1) -> 15079.845 | D27: =C27*rendimento_carteira -> 162.71152
A28: 10 | B28: Quantos em 10 anos? | C28: =FV($D$20,$A28*12,$D$18*-1) -> 43791.158 | D28: =C28*rendimento_carteira -> 472.5066
A29: 20 | B29: Quantos em 20 anos? | C29: =FV($D$20,$A29*12,$D$18*-1) -> 202535.71 | D29: =C29*rendimento_carteira -> 2185.3603
A30: 30 | B30: Quantos em 30 anos? | C30: =FV($D$20,$A30*12,$D$18*-1) -> 777990.54 | D30: =C30*rendimento_carteira -> 8394.5179
B34: PERFIL | C34: AGRESSIVO
B35: VALOR A SER INVESTIDO POR MÊS | C35: =aporte -> 180
B37: TIPO DE FII | C37: Percentual sugerido | D37: Valores
B38: PAPEL | C38: =VLOOKUP($C$34&"-"&B38,Planilha2!A:D,4,FALSE) -> 0.5 | D38: =$C$35*C38 -> 90
B39: TIJOLO | C39: =VLOOKUP($C$34&"-"&B39,Planilha2!A:D,4,FALSE) -> 0.1 | D39: =$C$35*C39 -> 18
B40: HÍBRIDOS | C40: =VLOOKUP($C$34&"-"&B40,Planilha2!A:D,4,FALSE) -> 0.05 | D40: =$C$35*C40 -> 9
B41: FOF's | C41: =VLOOKUP($C$34&"-"&B41,Planilha2!A:D,4,FALSE) -> 0.05 | D41: =$C$35*C41 -> 9
B42: DESENVOLVIMENTO | C42: =VLOOKUP($C$34&"-"&B42,Planilha2!A:D,4,FALSE) -> 0.2 | D42: =$C$35*C42 -> 36
B43: HOTELARIA | C43: =VLOOKUP($C$34&"-"&B43,Planilha2!A:D,4,FALSE) -> 0.1 | D43: =$C$35*C43 -> 18
D44: =SUM(D38:D43) -> 180

Sheet Planilha2
A2: Chave | B2: Perfil | C2: Tipo de FII | D2: %
A3: =B3&"-"&C3 -> CONSERVADOR-PAPEL | B3: CONSERVADOR | C3: PAPEL | D3: 0.3
A4: =B4&"-"&C4 -> CONSERVADOR-TIJOLO | B4: CONSERVADOR | C4: TIJOLO | D4: 0.5
A5: =B5&"-"&C5 -> CONSERVADOR-HÍBRIDOS | B5: CONSERVADOR | C5: HÍBRIDOS | D5: 0.1
A6: =B6&"-"&C6 -> CONSERVADOR-FOF's | B6: CONSERVADOR | C6: FOF's | D6: 0.1
A7: =B7&"-"&C7 -> CONSERVADOR-DESENVOLVIMENTO | B7: CONSERVADOR | C7: DESENVOLVIMENTO | D7: 0
A8: =B8&"-"&C8 -> CONSERVADOR-HOTELARIA | B8: CONSERVADOR | C8: HOTELARIA | D8: 0
A9: =B9&"-"&C9 -> MODERADO-PAPEL | B9: MODERADO | C9: PAPEL | D9: 0.32
A10: =B10&"-"&C10 -> MODERADO-TIJOLO | B10: MODERADO | C10: TIJOLO | D10: 0.4
A11: =B11&"-"&C11 -> MODERADO-HÍBRIDOS | B11: MODERADO | C11: HÍBRIDOS | D11: 0.1
A12: =B12&"-"&C12 -> MODERADO-FOF's | B12: MODERADO | C12: FOF's | D12: 0.08
A13: =B13&"-"&C13 -> MODERADO-DESENVOLVIMENTO | B13: MODERADO | C13: DESENVOLVIMENTO | D13: 0.05
A14: =B14&"-"&C14 -> MODERADO-HOTELARIA | B14: MODERADO | C14: HOTELARIA | D14: 0.05
... A20: =B20&"-"&C20 -> AGRESSIVO-HOTELARIA | B20: AGRESSIVO | C20: HOTELARIA | D20: 0.1
